{
  "version": 2,
  "extractor": "papercropper",
  "figures": [
    {
      "url": "assets/figures/arxiv/2605.24453v1/fig-001.webp",
      "caption": "",
      "page": 0,
      "index": 1,
      "width": 1292,
      "height": 2347,
      "label": "Figure"
    },
    {
      "url": "assets/figures/arxiv/2605.24453v1/fig-002.webp",
      "caption": "",
      "page": 0,
      "index": 2,
      "width": 1119,
      "height": 704,
      "label": "Figure"
    },
    {
      "url": "assets/figures/arxiv/2605.24453v1/fig-003.webp",
      "caption": "",
      "page": 0,
      "index": 3,
      "width": 1619,
      "height": 638,
      "label": "Figure"
    },
    {
      "url": "assets/figures/arxiv/2605.24453v1/fig-004.webp",
      "caption": "",
      "page": 0,
      "index": 4,
      "width": 1385,
      "height": 574,
      "label": "Figure"
    },
    {
      "url": "assets/figures/arxiv/2605.24453v1/fig-005.webp",
      "caption": "",
      "page": 0,
      "index": 5,
      "width": 1681,
      "height": 733,
      "label": "Figure"
    },
    {
      "url": "assets/figures/arxiv/2605.24453v1/fig-006.webp",
      "caption": "",
      "page": 0,
      "index": 6,
      "width": 1547,
      "height": 787,
      "label": "Figure"
    },
    {
      "url": "assets/figures/arxiv/2605.24453v1/fig-007.webp",
      "caption": "",
      "page": 0,
      "index": 7,
      "width": 1381,
      "height": 762,
      "label": "Figure"
    },
    {
      "url": "assets/figures/arxiv/2605.24453v1/fig-008.webp",
      "caption": "",
      "page": 0,
      "index": 8,
      "width": 1539,
      "height": 788,
      "label": "Figure"
    }
  ]
}